async_solipsism/__init__.py
async_solipsism/clock.py
async_solipsism/exceptions.py
async_solipsism/loop.py
async_solipsism/selector.py
async_solipsism/socket.py
async_solipsism-0.9.dist-info/licenses/LICENSE
async_solipsism-0.9.dist-info/METADATA
async_solipsism-0.9.dist-info/WHEEL
async_solipsism-0.9.dist-info/top_level.txt
async_solipsism-0.9.dist-info/RECORD
