Metadata-Version: 2.4
Name: async-solipsism
Version: 0.9
Summary: Asyncio event loop that doesn't interact with the outside world
Author-email: Bruce Merry <bmerry@gmail.com>
Project-URL: Homepage, https://github.com/bmerry/async-solipsism
Classifier: Development Status :: 5 - Production/Stable
Classifier: Framework :: AsyncIO
Classifier: License :: OSI Approved :: GNU General Public License v3 or later (GPLv3+)
Classifier: Topic :: Software Development :: Testing :: Mocking
Requires-Python: >=3.10
License-File: LICENSE
Provides-Extra: test
Requires-Dist: backports.asyncio.runner; python_version < "3.11" and extra == "test"
Requires-Dist: pre-commit; extra == "test"
Requires-Dist: pytest; extra == "test"
Requires-Dist: pytest-asyncio>=0.23; extra == "test"
Requires-Dist: pytest-mock; extra == "test"
Dynamic: license-file
